bdtrinity/__init__.py
bdtrinity/anomaly.py
bdtrinity/classification.py
bdtrinity/clustering.py
bdtrinity/datasets.py
bdtrinity/nlp.py
bdtrinity/regression.py
bdtrinity/time_series.py
bdtrinity/utils.py
bdtrinity-3.0.dist-info/LICENCE.txt
bdtrinity-3.0.dist-info/METADATA
bdtrinity-3.0.dist-info/WHEEL
bdtrinity-3.0.dist-info/top_level.txt
bdtrinity-3.0.dist-info/RECORD
