Metadata-Version: 2.1
Name: bdtrinity
Version: 3.0
Summary: BDTrinity - An open source, low-code machine learning library in Python.
Home-page: https://matrix-neo.gitbook.io/bd-trinity
Author: satish kumar
Author-email: sathishsriram999@gmail.com
License: MIT
Classifier: License :: OSI Approved :: MIT License
Classifier: Programming Language :: Python :: 3.9
Classifier: Programming Language :: Python :: 3.10
Classifier: Programming Language :: Python :: 3.11
License-File: LICENCE.txt
Requires-Dist: nltk==3.9.1
Requires-Dist: pycaret==3.3.2
Requires-Dist: vaderSentiment==3.3.2
Requires-Dist: multi-rake==0.0.1
Requires-Dist: langid==1.1.6
